matchbox/__init__.py
matchbox/database/__init__.py
matchbox/database/error.py
matchbox/models/__init__.py
matchbox/models/error.py
matchbox/models/field_validator.py
matchbox/models/fields.py
matchbox/models/managers.py
matchbox/models/models.py
matchbox/models/utils.py
matchbox/queries/__init__.py
matchbox/queries/error.py
matchbox/queries/paginator.py
matchbox/queries/queries.py
matchbox/queries/queries_result.py
matchbox/tests/__init__.py
matchbox/tests/test_field_validator.py
matchbox/tests/test_fields.py
matchbox/tests/test_model.py
matchbox_orm-0.2.7.dist-info/METADATA
matchbox_orm-0.2.7.dist-info/RECORD
matchbox_orm-0.2.7.dist-info/WHEEL
matchbox_orm-0.2.7.dist-info/top_level.txt
