Metadata-Version: 2.1
Name: matchbox-orm
Version: 0.2.7
Summary: matchbox is orm package for google Cloud Firestore
Home-page: https://github.com/gameboy86/matchbox
Author: Maciej Gębarski
Author-email: mgebarski@gmail.com
License: MIT
Keywords: firebase orm firestore google cloud
Platform: UNKNOWN
Classifier: License :: OSI Approved :: MIT License
Classifier: Intended Audience :: Developers
Classifier: Operating System :: OS Independent
Classifier: Programming Language :: Python :: 3
Classifier: Programming Language :: Python :: 3.4
Classifier: Programming Language :: Python :: 3.5
Classifier: Programming Language :: Python :: 3.6
Requires-Dist: firebase-admin (>=2.16.0)
Requires-Dist: iso8601 (>=0.1.12)
